phone_local/__init__.py
phone_local/phone_local_constans.py
phone_local/phones_local.py
phone_local-0.0.15.dist-info/METADATA
phone_local-0.0.15.dist-info/WHEEL
phone_local-0.0.15.dist-info/top_level.txt
phone_local-0.0.15.dist-info/RECORD
