Metadata-Version: 2.1
Name: phone-local
Version: 0.0.15
Home-page: https://github.com/circles-zone/phone-local-python-package
Author: Circles
Author-email: info@circles.life
Classifier: Programming Language :: Python :: 3
Classifier: License :: Other/Proprietary License
Classifier: Operating System :: OS Independent
Requires-Dist: logger-local >=0.0.76
Requires-Dist: database-mysql-local >=0.0.107
Requires-Dist: phonenumbers
